tax_bpjs/__init__.py
tax_bpjs/bpjs.py
tax_bpjs/tax.py
tax_bpjs/test/__init__.py
tax_bpjs/test/test_bpjs.py
tax_bpjs/test/test_cassette_bpjs.py
tax_bpjs/test/test_cassette_tax.py
tax_bpjs/test/test_tax.py
tax_bpjs-1.0.5.dist-info/LICENSE
tax_bpjs-1.0.5.dist-info/METADATA
tax_bpjs-1.0.5.dist-info/WHEEL
tax_bpjs-1.0.5.dist-info/top_level.txt
tax_bpjs-1.0.5.dist-info/RECORD
