Metadata-Version: 2.1
Name: tax-bpjs
Version: 1.0.5
Summary: Easy Tax & BPJS Calculation using Python!
Home-page: https://github.com/vousmeevoyez/tax_bpjs
Author: Kelvin Desman
Author-email: kelvindsmn@gmail.com
License: MIT
Platform: UNKNOWN
Classifier: Programming Language :: Python :: 3
Classifier: License :: OSI Approved :: MIT License
Classifier: Operating System :: OS Independent
Requires-Python: >=3
Requires-Dist: python-dateutil
